guikit/__init__.py
guikit/__main__.py
guikit/config.py
guikit/core.py
guikit/logging.py
guikit/plugins.py
guikit/progress.py
guikit/scripts.py
guikit/threads.py
guikit/extensions/__init__.py
guikit/extensions/about_dialog/__init__.py
guikit/extensions/about_dialog/about_dialog.py
guikit/extensions/about_dialog/description
guikit/extensions/about_dialog/licence
guikit/extensions/about_dialog/license
guikit/extensions/about_dialog/logo.png
guikit/extensions/example_plugin/__init__.py
guikit/extensions/example_plugin/central.py
guikit/extensions/example_plugin/menu.py
guikit/extensions/example_plugin/notebook.py
guikit/extensions/example_plugin/tools.py
guikit/extensions/load_data/MOCK_DATA.csv
guikit/extensions/load_data/__init__.py
guikit/extensions/load_data/model.py
guikit/extensions/load_data/presenter.py
guikit/extensions/load_data/view.py
guikit/skeleton/__init__.py
guikit/skeleton/__main__.py
guikit/skeleton/config.py
guikit/skeleton/extensions/__init__.py
tests/__init__.py
tests/conftest.py
tests/test_core.py
tests/test_logging.py
tests/test_plugins.py
tests/test_progress.py
tests/test_scripts.py
tests/test_threads.py
guikit-0.3.0.dist-info/LICENSE
guikit-0.3.0.dist-info/METADATA
guikit-0.3.0.dist-info/WHEEL
guikit-0.3.0.dist-info/top_level.txt
guikit-0.3.0.dist-info/RECORD
